Ripple_Carry_Adder/full_adder_module.v
module full_adder(
    input a,
    input b,
    input carry_in,
    output sum,
    output carry_out
);
    assign sum = a ^ b ^ carry_in;
    assign carry_out = (a & b) | (carry_in & (a ^ b));
endmodule

Full_Adder/full_adder_tb.v
module full_adder_tb;
    reg a;
    reg b;
    reg carry_in;
    wire sum;
    wire carry_out;

    // Instantiate the full adder
    full_adder uut (
        .a(a),
        .b(b),
        .carry_in(carry_in),
        .sum(sum),
        .carry_out(carry_out)
    );

    initial begin

        $dumpfile("full_adder_tb.vcd");
        $dumpvars(0, full_adder_tb);

        // Test case 1: 0 + 0 + 0
        a = 0; b = 0; carry_in = 0;
        #10; // Wait for 10 time units

        // Test case 2: 0 + 0 + 1
        a = 0; b = 0; carry_in = 1;
        #10;

        // Test case 3: 0 + 1 + 0
        a = 0; b = 1; carry_in = 0;
        #10;

        // Test case 4: 0 + 1 + 1
        a = 0; b = 1; carry_in = 1;
        #10;

        // Test case 5: 1 + 0 + 0
        a = 1; b = 0; carry_in = 0;
        #10;

        // Test case 6: 1 + 0 + 1
        a = 1; b = 0; carry_in = 1;
        #10;

        // Test case 7: 1 + 1 + 0
        a = 1; b = 1; carry_in = 0;
        #10;

        // Test case 8: 1 + 1 + 1
        a = 1; b = 1; carry_in = 1;
        #10;

        $finish; // End the simulation
    end
endmodule

full_adder_tb.vcd
$date
	Sat Jun 13 22:50:23 2026
$end
$version
	Icarus Verilog
$end
$timescale
	1s
$end
$scope module full_adder_tb $end
$var wire 1 ! sum $end
$var wire 1 " carry_out $end
$var reg 1 # a $end
$var reg 1 $ b $end
$var reg 1 % carry_in $end
$scope module uut $end
$var wire 1 # a $end
$var wire 1 $ b $end
$var wire 1 % carry_in $end
$var wire 1 " carry_out $end
$var wire 1 ! sum $end
$upscope $end
$upscope $end
$enddefinitions $end
$comment Show the parameter values. $end
$dumpall
$end
#0
$dumpvars
0%
0$
0#
0"
0!
$end
#10
1!
1%
#20
0%
1$
#30
1"
0!
1%
#40
0"
1!
0%
0$
1#
#50
1"
0!
1%
#60
0%
1$
#70
1!
1%
