Priority_Encoder/priority_encoder.v
module priority_encoer_8to3 (
    input [7:0] in,
    output reg [2:0] out,
    output reg valid
);
    always @(*) begin
        valid = 1'b0;
        out = 3'b000;
        if (in[7]) begin
            out = 3'b111;
            valid = 1'b1;
        end else if (in[6]) begin
            out = 3'b110;
            valid = 1'b1;
        end else if (in[5]) begin
            out = 3'b101;
            valid = 1'b1;
        end else if (in[4]) begin
            out = 3'b100;
            valid = 1'b1;
        end else if (in[3]) begin
            out = 3'b011;
            valid = 1'b1;
        end else if (in[2]) begin
            out = 3'b010;
            valid = 1'b1;
        end else if (in[1]) begin
            out = 3'b001;
            valid = 1'b1;
        end else if (in[0]) begin
            out = 3'b000;
            valid = 1'b1;
        end
    end

endmodule

Priority_Encoder/priority_encoder_tb.v
module priority_encoder_tb;

    reg [7:0] in;
    wire [2:0] out;
    wire valid;

    priority_encoer_8to3 uut (
        .in(in),
        .out(out),
        .valid(valid)
    );

    initial begin

        $dumpfile("priority_encoder_tb.vcd");
        $dumpvars(0, priority_encoder_tb);
        // Test case 1: Only D0 is high
        in = 8'b00000001;
        #10;
        $display("Input: %b, Output: %b, Valid: %b", in, out, valid);

        // Test case 2: D1 is high
        in = 8'b00000010;
        #10;
        $display("Input: %b, Output: %b, Valid: %b", in, out, valid);

        // Test case 3: D2 is high
        in = 8'b00000100;
        #10;
        $display("Input: %b, Output: %b, Valid: %b", in, out, valid);

        // Test case 4: D3 is high
        in = 8'b00001000;
        #10;
        $display("Input: %b, Output: %b, Valid: %b", in, out, valid);

        // Test case 5: D4 is high
        in = 8'b00010000;
        #10;
        $display("Input: %b, Output: %b, Valid: %b", in, out, valid);

        // Test case 6: D5 is high
        in = 8'b00100000;
        #10;
        $display("Input: %b, Output: %b, Valid: %b", in, out, valid);

        // Test case 7: D6 is high
        in = 8'b01000000;
        #10;

        // Test case 8: D7 is high
        in = 8'b10000000;
        #10;
        $display("Input: %b, Output: %b, Valid: %b", in, out, valid);

    end
endmodule

Priority_Encoder/priority_encoder_tb.vcd
$date
	Sat Jul 04 09:37:42 2026
$end
$version
	Icarus Verilog
$end
$timescale
	1s
$end
$scope module priority_encoder_tb $end
$var wire 1 ! valid $end
$var wire 3 " out [2:0] $end
$var reg 8 # in [7:0] $end
$scope module uut $end
$var wire 8 $ in [7:0] $end
$var reg 3 % out [2:0] $end
$var reg 1 ! valid $end
$upscope $end
$upscope $end
$enddefinitions $end
$comment Show the parameter values. $end
$dumpall
$end
#0
$dumpvars
b0 %
b1 $
b1 #
b0 "
1!
$end
#10
b1 "
b1 %
1!
b10 #
b10 $
#20
b10 "
b10 %
1!
b100 #
b100 $
#30
b11 "
b11 %
1!
b1000 #
b1000 $
#40
b100 "
b100 %
1!
b10000 #
b10000 $
#50
b101 "
b101 %
1!
b100000 #
b100000 $
#60
b110 "
b110 %
1!
b1000000 #
b1000000 $
#70
b111 "
b111 %
1!
b10000000 #
b10000000 $
