Ripple_Carry_Adder/full_adder_module.v
module full_adder(
    input a,
    input b,
    input carry_in,
    output sum,
    output carry_out
);
    assign sum = a ^ b ^ carry_in;
    assign carry_out = (a & b) | (carry_in & (a ^ b));
endmodule

Ripple_Carry_Adder/ripple_carry_adder.v
module ripple_carry_adder(
    input [3:0]a,
    input [3:0]b,
    input carry_in,
    output [3:0]sum,
    output carry_out
);
    wire c1, c2, c3;
    full_adder fa0 (
        .a(a[0]),
        .b(b[0]),
        .carry_in(carry_in),
        .sum(sum[0]),
        .carry_out(c1)  
    );
    full_adder fa1 (
        .a(a[1]),
        .b(b[1]),
        .carry_in(c1),
        .sum(sum[1]),
        .carry_out(c2)  
    );
    full_adder fa2 (
        .a(a[2]),
        .b(b[2]),
        .carry_in(c2),
        .sum(sum[2]),
        .carry_out(c3)
    );
    full_adder fa3 (
        .a(a[3]),
        .b(b[3]),
        .carry_in(c3),
        .sum(sum[3]),
        .carry_out(carry_out)
    );
    endmodule

Ripple_Carry_Adder/ripple_carry_adder_tb.v
module ripple_carry_adder_tb;
    reg [3:0] a;
    reg [3:0] b;
    reg carry_in;
    wire [3:0] sum;
    wire carry_out;

    integer i,j;

    ripple_carry_adder uut (
        .a(a),
        .b(b),
        .carry_in(carry_in),
        .sum(sum),
        .carry_out(carry_out)
    );
    initial begin
        $dumpfile("ripple_carry_adder_tb.vcd");
        $dumpvars(0, ripple_carry_adder_tb);

        $monitor("Time=%0t, a=%b, b=%b, carry_in=%b, sum=%b, carry_out=%b", $time, a, b, carry_in, sum, carry_out);

        //Test all possible combinations of inputs
        for (i = 0; i < 16; i = i + 1) begin
            for (j = 0; j < 16; j = j + 1) begin
                a = i;
                b = j;
                carry_in = 0; // Test with carry_in = 0
                #10;
                $display("Test case: a=%b, b=%b, carry_in=%b, sum=%b, carry_out=%b", a, b, carry_in, sum, carry_out);

                carry_in = 1; // Test with carry_in = 1
                #10;
                $display("Test case: a=%b, b=%b, carry_in=%b, sum=%b, carry_out=%b", a, b, carry_in, sum, carry_out);
            end
        end
        $finish;
    end    
endmodule

Ripple_Carry_Adder/ripple_carry_adder_tb.vcd
$date
	Thu Jun 18 15:46:01 2026
$end
$version
	Icarus Verilog
$end
$timescale
	1s
$end
$scope module ripple_carry_adder_tb $end
$var wire 4 ! sum [3:0] $end
$var wire 1 " carry_out $end
$var reg 4 # a [3:0] $end
$var reg 4 $ b [3:0] $end
$var reg 1 % carry_in $end
$var integer 32 & i [31:0] $end
$var integer 32 ' j [31:0] $end
$scope module uut $end
$var wire 4 ( a [3:0] $end
$var wire 4 ) b [3:0] $end
$var wire 1 % carry_in $end
$var wire 4 * sum [3:0] $end
$var wire 1 " carry_out $end
$var wire 1 + c3 $end
$var wire 1 , c2 $end
$var wire 1 - c1 $end
$scope module fa0 $end
$var wire 1 . a $end
$var wire 1 / b $end
$var wire 1 % carry_in $end
$var wire 1 - carry_out $end
$var wire 1 0 sum $end
$upscope $end
$scope module fa1 $end
$var wire 1 1 a $end
$var wire 1 2 b $end
$var wire 1 - carry_in $end
$var wire 1 , carry_out $end
$var wire 1 3 sum $end
$upscope $end
$scope module fa2 $end
$var wire 1 4 a $end
$var wire 1 5 b $end
$var wire 1 , carry_in $end
$var wire 1 + carry_out $end
$var wire 1 6 sum $end
$upscope $end
$scope module fa3 $end
$var wire 1 7 a $end
$var wire 1 8 b $end
$var wire 1 + carry_in $end
$var wire 1 " carry_out $end
$var wire 1 9 sum $end
$upscope $end
$upscope $end
$upscope $end
$enddefinitions $end
$comment Show the parameter values. $end
$dumpall
$end
#0
$dumpvars
09
08
07
06
05
04
03
02
01
00
0/
0.
0-
0,
0+
b0 *
b0 )
b0 (
b0 '
b0 &
0%
b0 $
b0 #
0"
b0 !
$end
#10
b1 !
b1 *
10
1%
#20
b1 !
b1 *
10
1/
0%
b1 $
b1 )
b1 '
#30
13
1-
b10 !
b10 *
00
1%
#40
0-
b10 !
b10 *
00
0/
12
0%
b10 $
b10 )
b10 '
#50
b11 !
b11 *
10
1%
#60
b11 !
b11 *
10
1/
0%
b11 $
b11 )
b11 '
#70
16
1,
03
1-
b100 !
b100 *
00
1%
#80
09
0,
0+
16
0-
b100 !
b100 *
00
0/
02
15
0%
b100 $
b100 )
b100 '
#90
b101 !
b101 *
10
1%
#100
b101 !
b101 *
10
1/
0%
b101 $
b101 )
b101 '
#110
13
1-
b110 !
b110 *
00
1%
#120
0-
b110 !
b110 *
00
0/
12
0%
b110 $
b110 )
b110 '
#130
b111 !
b111 *
10
1%
#140
b111 !
b111 *
10
1/
0%
b111 $
b111 )
b111 '
#150
19
1+
06
1,
03
1-
b1000 !
b1000 *
00
1%
#160
0,
0+
0"
06
19
0-
b1000 !
b1000 *
00
0/
02
05
18
0%
b1000 $
b1000 )
b1000 '
#170
b1001 !
b1001 *
10
1%
#180
b1001 !
b1001 *
10
1/
0%
b1001 $
b1001 )
b1001 '
#190
13
1-
b1010 !
b1010 *
00
1%
#200
0-
b1010 !
b1010 *
00
0/
12
0%
b1010 $
b1010 )
b1010 '
#210
b1011 !
b1011 *
10
1%
#220
b1011 !
b1011 *
10
1/
0%
b1011 $
b1011 )
b1011 '
#230
16
1,
03
1-
b1100 !
b1100 *
00
1%
#240
0"
19
0,
0+
16
0-
b1100 !
b1100 *
00
0/
02
15
0%
b1100 $
b1100 )
b1100 '
#250
b1101 !
b1101 *
10
1%
#260
b1101 !
b1101 *
10
1/
0%
b1101 $
b1101 )
b1101 '
#270
13
1-
b1110 !
b1110 *
00
1%
#280
0-
b1110 !
b1110 *
00
0/
12
0%
b1110 $
b1110 )
b1110 '
#290
b1111 !
b1111 *
10
1%
#300
b1111 !
b1111 *
10
1/
0%
b1111 $
b1111 )
b1111 '
#310
1"
09
1+
06
1,
03
1-
b0 !
b0 *
00
1%
#320
0,
0+
0"
06
09
0-
b1 !
b1 *
10
0/
02
05
08
1.
0%
b0 $
b0 )
b1 #
b1 (
b1 &
b0 '
#330
13
1-
b10 !
b10 *
00
1%
#340
b10 !
b10 *
00
1/
0%
b1 $
b1 )
b1 '
#350
b11 !
b11 *
10
1%
#360
06
0,
0-
13
b11 !
b11 *
10
0/
12
0%
b10 $
b10 )
b10 '
#370
16
1,
03
1-
b100 !
b100 *
00
1%
#380
b100 !
b100 *
00
1/
0%
b11 $
b11 )
b11 '
#390
b101 !
b101 *
10
1%
#400
09
0,
0+
0-
03
16
b101 !
b101 *
10
0/
02
15
0%
b100 $
b100 )
b100 '
#410
13
1-
b110 !
b110 *
00
1%
#420
b110 !
b110 *
00
1/
0%
b101 $
b101 )
b101 '
#430
b111 !
b111 *
10
1%
#440
09
0+
16
0,
0-
13
b111 !
b111 *
10
0/
12
0%
b110 $
b110 )
b110 '
#450
19
1+
06
1,
03
1-
b1000 !
b1000 *
00
1%
#460
b1000 !
b1000 *
00
1/
0%
b111 $
b111 )
b111 '
#470
b1001 !
b1001 *
10
1%
#480
0,
0+
0"
0-
03
06
19
b1001 !
b1001 *
10
0/
02
05
18
0%
b1000 $
b1000 )
b1000 '
#490
13
1-
b1010 !
b1010 *
00
1%
#500
b1010 !
b1010 *
00
1/
0%
b1001 $
b1001 )
b1001 '
#510
b1011 !
b1011 *
10
1%
#520
06
0,
0-
13
b1011 !
b1011 *
10
0/
12
0%
b1010 $
b1010 )
b1010 '
#530
16
1,
03
1-
b1100 !
b1100 *
00
1%
#540
b1100 !
b1100 *
00
1/
0%
b1011 $
b1011 )
b1011 '
#550
b1101 !
b1101 *
10
1%
#560
0"
19
0,
0+
0-
03
16
b1101 !
b1101 *
10
0/
02
15
0%
b1100 $
b1100 )
b1100 '
#570
13
1-
b1110 !
b1110 *
00
1%
#580
b1110 !
b1110 *
00
1/
0%
b1101 $
b1101 )
b1101 '
#590
b1111 !
b1111 *
10
1%
#600
0"
19
0+
16
0,
0-
13
b1111 !
b1111 *
10
0/
12
0%
b1110 $
b1110 )
b1110 '
#610
1"
09
1+
06
1,
03
1-
b0 !
b0 *
00
1%
#620
b0 !
b0 *
00
1/
0%
b1111 $
b1111 )
b1111 '
#630
b1 !
b1 *
10
1%
#640
0,
0+
0"
13
06
09
0-
b10 !
b10 *
00
0/
02
05
08
0.
11
0%
b0 $
b0 )
b10 #
b10 (
b10 &
b0 '
#650
b11 !
b11 *
10
1%
#660
b11 !
b11 *
10
1/
0%
b1 $
b1 )
b1 '
#670
16
1,
03
1-
b100 !
b100 *
00
1%
#680
0-
b100 !
b100 *
00
0/
12
0%
b10 $
b10 )
b10 '
#690
b101 !
b101 *
10
1%
#700
b101 !
b101 *
10
1/
0%
b11 $
b11 )
b11 '
#710
13
1-
b110 !
b110 *
00
1%
#720
09
0+
0,
16
0-
b110 !
b110 *
00
0/
02
15
0%
b100 $
b100 )
b100 '
#730
b111 !
b111 *
10
1%
#740
b111 !
b111 *
10
1/
0%
b101 $
b101 )
b101 '
#750
19
1+
06
1,
03
1-
b1000 !
b1000 *
00
1%
#760
0-
b1000 !
b1000 *
00
0/
12
0%
b110 $
b110 )
b110 '
#770
b1001 !
b1001 *
10
1%
#780
b1001 !
b1001 *
10
1/
0%
b111 $
b111 )
b111 '
#790
13
1-
b1010 !
b1010 *
00
1%
#800
0+
0"
0,
06
19
0-
b1010 !
b1010 *
00
0/
02
05
18
0%
b1000 $
b1000 )
b1000 '
#810
b1011 !
b1011 *
10
1%
#820
b1011 !
b1011 *
10
1/
0%
b1001 $
b1001 )
b1001 '
#830
16
1,
03
1-
b1100 !
b1100 *
00
1%
#840
0-
b1100 !
b1100 *
00
0/
12
0%
b1010 $
b1010 )
b1010 '
#850
b1101 !
b1101 *
10
1%
#860
b1101 !
b1101 *
10
1/
0%
b1011 $
b1011 )
b1011 '
#870
13
1-
b1110 !
b1110 *
00
1%
#880
0"
19
0+
0,
16
0-
b1110 !
b1110 *
00
0/
02
15
0%
b1100 $
b1100 )
b1100 '
#890
b1111 !
b1111 *
10
1%
#900
b1111 !
b1111 *
10
1/
0%
b1101 $
b1101 )
b1101 '
#910
1"
09
1+
06
1,
03
1-
b0 !
b0 *
00
1%
#920
0-
b0 !
b0 *
00
0/
12
0%
b1110 $
b1110 )
b1110 '
#930
b1 !
b1 *
10
1%
#940
b1 !
b1 *
10
1/
0%
b1111 $
b1111 )
b1111 '
#950
13
1-
b10 !
b10 *
00
1%
#960
0+
0"
0,
06
09
0-
b11 !
b11 *
10
0/
02
05
08
1.
0%
b0 $
b0 )
b11 #
b11 (
b11 &
b0 '
#970
16
1,
03
1-
b100 !
b100 *
00
1%
#980
b100 !
b100 *
00
1/
0%
b1 $
b1 )
b1 '
#990
b101 !
b101 *
10
1%
#1000
0-
03
b101 !
b101 *
10
0/
12
0%
b10 $
b10 )
b10 '
#1010
13
1-
b110 !
b110 *
00
1%
#1020
b110 !
b110 *
00
1/
0%
b11 $
b11 )
b11 '
#1030
b111 !
b111 *
10
1%
#1040
0,
09
0+
0-
13
16
b111 !
b111 *
10
0/
02
15
0%
b100 $
b100 )
b100 '
#1050
19
1+
06
1,
03
1-
b1000 !
b1000 *
00
1%
#1060
b1000 !
b1000 *
00
1/
0%
b101 $
b101 )
b101 '
#1070
b1001 !
b1001 *
10
1%
#1080
0-
03
b1001 !
b1001 *
10
0/
12
0%
b110 $
b110 )
b110 '
#1090
13
1-
b1010 !
b1010 *
00
1%
#1100
b1010 !
b1010 *
00
1/
0%
b111 $
b111 )
b111 '
#1110
b1011 !
b1011 *
10
1%
#1120
0,
0+
0"
0-
13
06
19
b1011 !
b1011 *
10
0/
02
05
18
0%
b1000 $
b1000 )
b1000 '
#1130
16
1,
03
1-
b1100 !
b1100 *
00
1%
#1140
b1100 !
b1100 *
00
1/
0%
b1001 $
b1001 )
b1001 '
#1150
b1101 !
b1101 *
10
1%
#1160
0-
03
b1101 !
b1101 *
10
0/
12
0%
b1010 $
b1010 )
b1010 '
#1170
13
1-
b1110 !
b1110 *
00
1%
#1180
b1110 !
b1110 *
00
1/
0%
b1011 $
b1011 )
b1011 '
#1190
b1111 !
b1111 *
10
1%
#1200
0"
0,
19
0+
0-
13
16
b1111 !
b1111 *
10
0/
02
15
0%
b1100 $
b1100 )
b1100 '
#1210
1"
09
1+
06
1,
03
1-
b0 !
b0 *
00
1%
#1220
b0 !
b0 *
00
1/
0%
b1101 $
b1101 )
b1101 '
#1230
b1 !
b1 *
10
1%
#1240
0-
03
b1 !
b1 *
10
0/
12
0%
b1110 $
b1110 )
b1110 '
#1250
13
1-
b10 !
b10 *
00
1%
#1260
b10 !
b10 *
00
1/
0%
b1111 $
b1111 )
b1111 '
#1270
b11 !
b11 *
10
1%
#1280
0+
0"
03
16
09
0-
0,
b100 !
b100 *
00
0/
02
05
08
0.
01
14
0%
b0 $
b0 )
b100 #
b100 (
b100 &
b0 '
#1290
b101 !
b101 *
10
1%
#1300
b101 !
b101 *
10
1/
0%
b1 $
b1 )
b1 '
#1310
13
1-
b110 !
b110 *
00
1%
#1320
0-
b110 !
b110 *
00
0/
12
0%
b10 $
b10 )
b10 '
#1330
b111 !
b111 *
10
1%
#1340
b111 !
b111 *
10
1/
0%
b11 $
b11 )
b11 '
#1350
19
1+
06
1,
03
1-
b1000 !
b1000 *
00
1%
#1360
0,
06
0-
b1000 !
b1000 *
00
0/
02
15
0%
b100 $
b100 )
b100 '
#1370
b1001 !
b1001 *
10
1%
#1380
b1001 !
b1001 *
10
1/
0%
b101 $
b101 )
b101 '
#1390
13
1-
b1010 !
b1010 *
00
1%
#1400
0-
b1010 !
b1010 *
00
0/
12
0%
b110 $
b110 )
b110 '
#1410
b1011 !
b1011 *
10
1%
#1420
b1011 !
b1011 *
10
1/
0%
b111 $
b111 )
b111 '
#1430
16
1,
03
1-
b1100 !
b1100 *
00
1%
#1440
0+
0,
0"
16
19
0-
b1100 !
b1100 *
00
0/
02
05
18
0%
b1000 $
b1000 )
b1000 '
#1450
b1101 !
b1101 *
10
1%
#1460
b1101 !
b1101 *
10
1/
0%
b1001 $
b1001 )
b1001 '
#1470
13
1-
b1110 !
b1110 *
00
1%
#1480
0-
b1110 !
b1110 *
00
0/
12
0%
b1010 $
b1010 )
b1010 '
#1490
b1111 !
b1111 *
10
1%
#1500
b1111 !
b1111 *
10
1/
0%
b1011 $
b1011 )
b1011 '
#1510
1"
09
1+
06
1,
03
1-
b0 !
b0 *
00
1%
#1520
0,
06
0-
b0 !
b0 *
00
0/
02
15
0%
b1100 $
b1100 )
b1100 '
#1530
b1 !
b1 *
10
1%
#1540
b1 !
b1 *
10
1/
0%
b1101 $
b1101 )
b1101 '
#1550
13
1-
b10 !
b10 *
00
1%
#1560
0-
b10 !
b10 *
00
0/
12
0%
b1110 $
b1110 )
b1110 '
#1570
b11 !
b11 *
10
1%
#1580
b11 !
b11 *
10
1/
0%
b1111 $
b1111 )
b1111 '
#1590
16
1,
03
1-
b100 !
b100 *
00
1%
#1600
0+
0,
0"
16
09
0-
b101 !
b101 *
10
0/
02
05
08
1.
0%
b0 $
b0 )
b101 #
b101 (
b101 &
b0 '
#1610
13
1-
b110 !
b110 *
00
1%
#1620
b110 !
b110 *
00
1/
0%
b1 $
b1 )
b1 '
#1630
b111 !
b111 *
10
1%
#1640
09
0+
16
0,
0-
13
b111 !
b111 *
10
0/
12
0%
b10 $
b10 )
b10 '
#1650
19
1+
06
1,
03
1-
b1000 !
b1000 *
00
1%
#1660
b1000 !
b1000 *
00
1/
0%
b11 $
b11 )
b11 '
#1670
b1001 !
b1001 *
10
1%
#1680
0,
0-
03
06
b1001 !
b1001 *
10
0/
02
15
0%
b100 $
b100 )
b100 '
#1690
13
1-
b1010 !
b1010 *
00
1%
#1700
b1010 !
b1010 *
00
1/
0%
b101 $
b101 )
b101 '
#1710
b1011 !
b1011 *
10
1%
#1720
06
0,
0-
13
b1011 !
b1011 *
10
0/
12
0%
b110 $
b110 )
b110 '
#1730
16
1,
03
1-
b1100 !
b1100 *
00
1%
#1740
b1100 !
b1100 *
00
1/
0%
b111 $
b111 )
b111 '
#1750
b1101 !
b1101 *
10
1%
#1760
0+
0,
0"
0-
03
16
19
b1101 !
b1101 *
10
0/
02
05
18
0%
b1000 $
b1000 )
b1000 '
#1770
13
1-
b1110 !
b1110 *
00
1%
#1780
b1110 !
b1110 *
00
1/
0%
b1001 $
b1001 )
b1001 '
#1790
b1111 !
b1111 *
10
1%
#1800
0"
19
0+
16
0,
0-
13
b1111 !
b1111 *
10
0/
12
0%
b1010 $
b1010 )
b1010 '
#1810
1"
09
1+
06
1,
03
1-
b0 !
b0 *
00
1%
#1820
b0 !
b0 *
00
1/
0%
b1011 $
b1011 )
b1011 '
#1830
b1 !
b1 *
10
1%
#1840
0,
0-
03
06
b1 !
b1 *
10
0/
02
15
0%
b1100 $
b1100 )
b1100 '
#1850
13
1-
b10 !
b10 *
00
1%
#1860
b10 !
b10 *
00
1/
0%
b1101 $
b1101 )
b1101 '
#1870
b11 !
b11 *
10
1%
#1880
06
0,
0-
13
b11 !
b11 *
10
0/
12
0%
b1110 $
b1110 )
b1110 '
#1890
16
1,
03
1-
b100 !
b100 *
00
1%
#1900
b100 !
b100 *
00
1/
0%
b1111 $
b1111 )
b1111 '
#1910
b101 !
b101 *
10
1%
#1920
0+
0,
0"
13
16
09
0-
b110 !
b110 *
00
0/
02
05
08
0.
11
0%
b0 $
b0 )
b110 #
b110 (
b110 &
b0 '
#1930
b111 !
b111 *
10
1%
#1940
b111 !
b111 *
10
1/
0%
b1 $
b1 )
b1 '
#1950
19
1+
06
1,
03
1-
b1000 !
b1000 *
00
1%
#1960
0-
b1000 !
b1000 *
00
0/
12
0%
b10 $
b10 )
b10 '
#1970
b1001 !
b1001 *
10
1%
#1980
b1001 !
b1001 *
10
1/
0%
b11 $
b11 )
b11 '
#1990
13
1-
b1010 !
b1010 *
00
1%
#2000
0,
06
0-
b1010 !
b1010 *
00
0/
02
15
0%
b100 $
b100 )
b100 '
#2010
b1011 !
b1011 *
10
1%
#2020
b1011 !
b1011 *
10
1/
0%
b101 $
b101 )
b101 '
#2030
16
1,
03
1-
b1100 !
b1100 *
00
1%
#2040
0-
b1100 !
b1100 *
00
0/
12
0%
b110 $
b110 )
b110 '
#2050
b1101 !
b1101 *
10
1%
#2060
b1101 !
b1101 *
10
1/
0%
b111 $
b111 )
b111 '
#2070
13
1-
b1110 !
b1110 *
00
1%
#2080
0+
0"
0,
16
19
0-
b1110 !
b1110 *
00
0/
02
05
18
0%
b1000 $
b1000 )
b1000 '
#2090
b1111 !
b1111 *
10
1%
#2100
b1111 !
b1111 *
10
1/
0%
b1001 $
b1001 )
b1001 '
#2110
1"
09
1+
06
1,
03
1-
b0 !
b0 *
00
1%
#2120
0-
b0 !
b0 *
00
0/
12
0%
b1010 $
b1010 )
b1010 '
#2130
b1 !
b1 *
10
1%
#2140
b1 !
b1 *
10
1/
0%
b1011 $
b1011 )
b1011 '
#2150
13
1-
b10 !
b10 *
00
1%
#2160
0,
06
0-
b10 !
b10 *
00
0/
02
15
0%
b1100 $
b1100 )
b1100 '
#2170
b11 !
b11 *
10
1%
#2180
b11 !
b11 *
10
1/
0%
b1101 $
b1101 )
b1101 '
#2190
16
1,
03
1-
b100 !
b100 *
00
1%
#2200
0-
b100 !
b100 *
00
0/
12
0%
b1110 $
b1110 )
b1110 '
#2210
b101 !
b101 *
10
1%
#2220
b101 !
b101 *
10
1/
0%
b1111 $
b1111 )
b1111 '
#2230
13
1-
b110 !
b110 *
00
1%
#2240
0+
0"
0,
16
09
0-
b111 !
b111 *
10
0/
02
05
08
1.
0%
b0 $
b0 )
b111 #
b111 (
b111 &
b0 '
#2250
19
1+
06
1,
03
1-
b1000 !
b1000 *
00
1%
#2260
b1000 !
b1000 *
00
1/
0%
b1 $
b1 )
b1 '
#2270
b1001 !
b1001 *
10
1%
#2280
0-
03
b1001 !
b1001 *
10
0/
12
0%
b10 $
b10 )
b10 '
#2290
13
1-
b1010 !
b1010 *
00
1%
#2300
b1010 !
b1010 *
00
1/
0%
b11 $
b11 )
b11 '
#2310
b1011 !
b1011 *
10
1%
#2320
0,
0-
13
06
b1011 !
b1011 *
10
0/
02
15
0%
b100 $
b100 )
b100 '
#2330
16
1,
03
1-
b1100 !
b1100 *
00
1%
#2340
b1100 !
b1100 *
00
1/
0%
b101 $
b101 )
b101 '
#2350
b1101 !
b1101 *
10
1%
#2360
0-
03
b1101 !
b1101 *
10
0/
12
0%
b110 $
b110 )
b110 '
#2370
13
1-
b1110 !
b1110 *
00
1%
#2380
b1110 !
b1110 *
00
1/
0%
b111 $
b111 )
b111 '
#2390
b1111 !
b1111 *
10
1%
#2400
0+
0,
0"
0-
13
16
19
b1111 !
b1111 *
10
0/
02
05
18
0%
b1000 $
b1000 )
b1000 '
#2410
1"
09
1+
06
1,
03
1-
b0 !
b0 *
00
1%
#2420
b0 !
b0 *
00
1/
0%
b1001 $
b1001 )
b1001 '
#2430
b1 !
b1 *
10
1%
#2440
0-
03
b1 !
b1 *
10
0/
12
0%
b1010 $
b1010 )
b1010 '
#2450
13
1-
b10 !
b10 *
00
1%
#2460
b10 !
b10 *
00
1/
0%
b1011 $
b1011 )
b1011 '
#2470
b11 !
b11 *
10
1%
#2480
0,
0-
13
06
b11 !
b11 *
10
0/
02
15
0%
b1100 $
b1100 )
b1100 '
#2490
16
1,
03
1-
b100 !
b100 *
00
1%
#2500
b100 !
b100 *
00
1/
0%
b1101 $
b1101 )
b1101 '
#2510
b101 !
b101 *
10
1%
#2520
0-
03
b101 !
b101 *
10
0/
12
0%
b1110 $
b1110 )
b1110 '
#2530
13
1-
b110 !
b110 *
00
1%
#2540
b110 !
b110 *
00
1/
0%
b1111 $
b1111 )
b1111 '
#2550
b111 !
b111 *
10
1%
#2560
0"
03
06
19
0-
0,
0+
b1000 !
b1000 *
00
0/
02
05
08
0.
01
04
17
0%
b0 $
b0 )
b1000 #
b1000 (
b1000 &
b0 '
#2570
b1001 !
b1001 *
10
1%
#2580
b1001 !
b1001 *
10
1/
0%
b1 $
b1 )
b1 '
#2590
13
1-
b1010 !
b1010 *
00
1%
#2600
0-
b1010 !
b1010 *
00
0/
12
0%
b10 $
b10 )
b10 '
#2610
b1011 !
b1011 *
10
1%
#2620
b1011 !
b1011 *
10
1/
0%
b11 $
b11 )
b11 '
#2630
16
1,
03
1-
b1100 !
b1100 *
00
1%
#2640
0"
19
0,
0+
16
0-
b1100 !
b1100 *
00
0/
02
15
0%
b100 $
b100 )
b100 '
#2650
b1101 !
b1101 *
10
1%
#2660
b1101 !
b1101 *
10
1/
0%
b101 $
b101 )
b101 '
#2670
13
1-
b1110 !
b1110 *
00
1%
#2680
0-
b1110 !
b1110 *
00
0/
12
0%
b110 $
b110 )
b110 '
#2690
b1111 !
b1111 *
10
1%
#2700
b1111 !
b1111 *
10
1/
0%
b111 $
b111 )
b111 '
#2710
1"
09
1+
06
1,
03
1-
b0 !
b0 *
00
1%
#2720
0,
0+
06
09
0-
b0 !
b0 *
00
0/
02
05
18
0%
b1000 $
b1000 )
b1000 '
#2730
b1 !
b1 *
10
1%
#2740
b1 !
b1 *
10
1/
0%
b1001 $
b1001 )
b1001 '
#2750
13
1-
b10 !
b10 *
00
1%
#2760
0-
b10 !
b10 *
00
0/
12
0%
b1010 $
b1010 )
b1010 '
#2770
b11 !
b11 *
10
1%
#2780
b11 !
b11 *
10
1/
0%
b1011 $
b1011 )
b1011 '
#2790
16
1,
03
1-
b100 !
b100 *
00
1%
#2800
09
0,
0+
16
0-
b100 !
b100 *
00
0/
02
15
0%
b1100 $
b1100 )
b1100 '
#2810
b101 !
b101 *
10
1%
#2820
b101 !
b101 *
10
1/
0%
b1101 $
b1101 )
b1101 '
#2830
13
1-
b110 !
b110 *
00
1%
#2840
0-
b110 !
b110 *
00
0/
12
0%
b1110 $
b1110 )
b1110 '
#2850
b111 !
b111 *
10
1%
#2860
b111 !
b111 *
10
1/
0%
b1111 $
b1111 )
b1111 '
#2870
19
1+
06
1,
03
1-
b1000 !
b1000 *
00
1%
#2880
0"
0,
0+
06
19
0-
b1001 !
b1001 *
10
0/
02
05
08
1.
0%
b0 $
b0 )
b1001 #
b1001 (
b1001 &
b0 '
#2890
13
1-
b1010 !
b1010 *
00
1%
#2900
b1010 !
b1010 *
00
1/
0%
b1 $
b1 )
b1 '
#2910
b1011 !
b1011 *
10
1%
#2920
06
0,
0-
13
b1011 !
b1011 *
10
0/
12
0%
b10 $
b10 )
b10 '
#2930
16
1,
03
1-
b1100 !
b1100 *
00
1%
#2940
b1100 !
b1100 *
00
1/
0%
b11 $
b11 )
b11 '
#2950
b1101 !
b1101 *
10
1%
#2960
0"
19
0,
0+
0-
03
16
b1101 !
b1101 *
10
0/
02
15
0%
b100 $
b100 )
b100 '
#2970
13
1-
b1110 !
b1110 *
00
1%
#2980
b1110 !
b1110 *
00
1/
0%
b101 $
b101 )
b101 '
#2990
b1111 !
b1111 *
10
1%
#3000
0"
19
0+
16
0,
0-
13
b1111 !
b1111 *
10
0/
12
0%
b110 $
b110 )
b110 '
#3010
1"
09
1+
06
1,
03
1-
b0 !
b0 *
00
1%
#3020
b0 !
b0 *
00
1/
0%
b111 $
b111 )
b111 '
#3030
b1 !
b1 *
10
1%
#3040
0,
0+
0-
03
06
09
b1 !
b1 *
10
0/
02
05
18
0%
b1000 $
b1000 )
b1000 '
#3050
13
1-
b10 !
b10 *
00
1%
#3060
b10 !
b10 *
00
1/
0%
b1001 $
b1001 )
b1001 '
#3070
b11 !
b11 *
10
1%
#3080
06
0,
0-
13
b11 !
b11 *
10
0/
12
0%
b1010 $
b1010 )
b1010 '
#3090
16
1,
03
1-
b100 !
b100 *
00
1%
#3100
b100 !
b100 *
00
1/
0%
b1011 $
b1011 )
b1011 '
#3110
b101 !
b101 *
10
1%
#3120
09
0,
0+
0-
03
16
b101 !
b101 *
10
0/
02
15
0%
b1100 $
b1100 )
b1100 '
#3130
13
1-
b110 !
b110 *
00
1%
#3140
b110 !
b110 *
00
1/
0%
b1101 $
b1101 )
b1101 '
#3150
b111 !
b111 *
10
1%
#3160
09
0+
16
0,
0-
13
b111 !
b111 *
10
0/
12
0%
b1110 $
b1110 )
b1110 '
#3170
19
1+
06
1,
03
1-
b1000 !
b1000 *
00
1%
#3180
b1000 !
b1000 *
00
1/
0%
b1111 $
b1111 )
b1111 '
#3190
b1001 !
b1001 *
10
1%
#3200
0"
0,
0+
13
06
19
0-
b1010 !
b1010 *
00
0/
02
05
08
0.
11
0%
b0 $
b0 )
b1010 #
b1010 (
b1010 &
b0 '
#3210
b1011 !
b1011 *
10
1%
#3220
b1011 !
b1011 *
10
1/
0%
b1 $
b1 )
b1 '
#3230
16
1,
03
1-
b1100 !
b1100 *
00
1%
#3240
0-
b1100 !
b1100 *
00
0/
12
0%
b10 $
b10 )
b10 '
#3250
b1101 !
b1101 *
10
1%
#3260
b1101 !
b1101 *
10
1/
0%
b11 $
b11 )
b11 '
#3270
13
1-
b1110 !
b1110 *
00
1%
#3280
0"
19
0+
0,
16
0-
b1110 !
b1110 *
00
0/
02
15
0%
b100 $
b100 )
b100 '
#3290
b1111 !
b1111 *
10
1%
#3300
b1111 !
b1111 *
10
1/
0%
b101 $
b101 )
b101 '
#3310
1"
09
1+
06
1,
03
1-
b0 !
b0 *
00
1%
#3320
0-
b0 !
b0 *
00
0/
12
0%
b110 $
b110 )
b110 '
#3330
b1 !
b1 *
10
1%
#3340
b1 !
b1 *
10
1/
0%
b111 $
b111 )
b111 '
#3350
13
1-
b10 !
b10 *
00
1%
#3360
0+
0,
06
09
0-
b10 !
b10 *
00
0/
02
05
18
0%
b1000 $
b1000 )
b1000 '
#3370
b11 !
b11 *
10
1%
#3380
b11 !
b11 *
10
1/
0%
b1001 $
b1001 )
b1001 '
#3390
16
1,
03
1-
b100 !
b100 *
00
1%
#3400
0-
b100 !
b100 *
00
0/
12
0%
b1010 $
b1010 )
b1010 '
#3410
b101 !
b101 *
10
1%
#3420
b101 !
b101 *
10
1/
0%
b1011 $
b1011 )
b1011 '
#3430
13
1-
b110 !
b110 *
00
1%
#3440
09
0+
0,
16
0-
b110 !
b110 *
00
0/
02
15
0%
b1100 $
b1100 )
b1100 '
#3450
b111 !
b111 *
10
1%
#3460
b111 !
b111 *
10
1/
0%
b1101 $
b1101 )
b1101 '
#3470
19
1+
06
1,
03
1-
b1000 !
b1000 *
00
1%
#3480
0-
b1000 !
b1000 *
00
0/
12
0%
b1110 $
b1110 )
b1110 '
#3490
b1001 !
b1001 *
10
1%
#3500
b1001 !
b1001 *
10
1/
0%
b1111 $
b1111 )
b1111 '
#3510
13
1-
b1010 !
b1010 *
00
1%
#3520
0"
0+
0,
06
19
0-
b1011 !
b1011 *
10
0/
02
05
08
1.
0%
b0 $
b0 )
b1011 #
b1011 (
b1011 &
b0 '
#3530
16
1,
03
1-
b1100 !
b1100 *
00
1%
#3540
b1100 !
b1100 *
00
1/
0%
b1 $
b1 )
b1 '
#3550
b1101 !
b1101 *
10
1%
#3560
0-
03
b1101 !
b1101 *
10
0/
12
0%
b10 $
b10 )
b10 '
#3570
13
1-
b1110 !
b1110 *
00
1%
#3580
b1110 !
b1110 *
00
1/
0%
b11 $
b11 )
b11 '
#3590
b1111 !
b1111 *
10
1%
#3600
0"
0,
19
0+
0-
13
16
b1111 !
b1111 *
10
0/
02
15
0%
b100 $
b100 )
b100 '
#3610
1"
09
1+
06
1,
03
1-
b0 !
b0 *
00
1%
#3620
b0 !
b0 *
00
1/
0%
b101 $
b101 )
b101 '
#3630
b1 !
b1 *
10
1%
#3640
0-
03
b1 !
b1 *
10
0/
12
0%
b110 $
b110 )
b110 '
#3650
13
1-
b10 !
b10 *
00
1%
