Encoder/encoder.v
module encoder_8to3 (
    input D0,
    input D1,
    input D2,
    input D3,
    input D4,
    input D5,
    input D6,
    input D7,
    output reg Y2,
    output reg Y1,
    output reg Y0

);

always @(*) begin
    case ({D7, D6, D5, D4, D3, D2, D1, D0})
        8'b00000001: begin
            Y2 = 0;
            Y1 = 0;
            Y0 = 0;
        end
        8'b00000010: begin
            Y2 = 0;
            Y1 = 0;
            Y0 = 1;
        end
        8'b00000100: begin
            Y2 = 0;
            Y1 = 1;
            Y0 = 0;
        end
        8'b00001000: begin
            Y2 = 0;
            Y1 = 1;
            Y0 = 1;
        end
        8'b00010000: begin
            Y2 = 1;
            Y1 = 0;
            Y0 = 0;
        end
        8'b00100000: begin
            Y2 = 1;
            Y1 = 0;
            Y0 = 1;
        end
        8'b01000000: begin
            Y2 = 1;
            Y1 = 1;
            Y0 = 0;
        end
        8'b10000000: begin
            Y2 = 1;
            Y1 = 1;
            Y0 = 1;
        end
        default: begin
            Y2 = 'bx;
            Y1 = 'bx; 
            Y0 = 'bx; 
        end
    endcase
end
endmodule

Encoder/encoder_tb.v
module encoder_8to3_tb;
reg D0, D1, D2, D3, D4, D5, D6, D7;
wire Y2, Y1, Y0;

encoder_8to3 uut (
    .D0(D0),
    .D1(D1),
    .D2(D2),
    .D3(D3),
    .D4(D4),
    .D5(D5),
    .D6(D6),
    .D7(D7),
    .Y2(Y2),
    .Y1(Y1),
    .Y0(Y0)
);
initial begin
    $dumpfile("encoder_8to3_tb.vcd");
    $dumpvars(0, encoder_8to3_tb);

    $monitor("Time=%0t, D7=%b, D6=%b, D5=%b, D4=%b, D3=%b, D2=%b, D1=%b, D0=%b, Y2=%b, Y1=%b, Y0=%b", $time, D7, D6, D5, D4, D3, D2, D1, D0, Y2, Y1, Y0);
    // Test case 1:
    D7 = 0; D6 = 0; D5 = 0; D4 = 0; D3 = 0; D2 = 0; D1 = 0; D0 = 1; #10;
    // Test case 2:
    D7 = 0; D6 = 0; D5 = 0; D4 = 0; D3 = 0; D2 = 0; D1 = 1; D0 = 0; #10;
    // Test case 3:
    D7 = 0; D6 = 0; D5 = 0; D4 = 0; D3 = 0; D2 = 1; D1 = 0; D0 = 0; #10;
    // Test case 4:
    D7 = 0; D6 = 0; D5 = 0; D4 = 0; D3 = 1; D2 = 0; D1 = 0; D0 = 0; #10;
    // Test case 5:
    D7 = 0; D6 = 0; D5 = 0; D4 = 1; D3 = 0; D2 = 0; D1 = 0; D0 = 0; #10;
    // Test case 6:
    D7 = 0; D6 = 0; D5 = 1; D4 = 0; D3 = 0; D2 = 0; D1 = 0; D0 = 0; #10;
    // Test case 7:
    D7 = 0; D6 = 1; D5 = 0; D4 = 0; D3 = 0; D2 = 0; D1 = 0; D0 = 0; #10;
    // Test case 8:
    D7 = 0; D6 = 0; D5 = 0; D4 = 0; D3 = 0; D2 = 0; D1 = 0; D0 = 0; #10;
end
endmodule

Encoder/encoder_8to3_tb.vcd
$date
	Mon Jun 22 17:51:14 2026
$end
$version
	Icarus Verilog
$end
$timescale
	1s
$end
$scope module encoder_8to3_tb $end
$var wire 1 ! Y2 $end
$var wire 1 " Y1 $end
$var wire 1 # Y0 $end
$var reg 1 $ D0 $end
$var reg 1 % D1 $end
$var reg 1 & D2 $end
$var reg 1 ' D3 $end
$var reg 1 ( D4 $end
$var reg 1 ) D5 $end
$var reg 1 * D6 $end
$var reg 1 + D7 $end
$scope module uut $end
$var wire 1 $ D0 $end
$var wire 1 % D1 $end
$var wire 1 & D2 $end
$var wire 1 ' D3 $end
$var wire 1 ( D4 $end
$var wire 1 ) D5 $end
$var wire 1 * D6 $end
$var wire 1 + D7 $end
$var reg 1 # Y0 $end
$var reg 1 " Y1 $end
$var reg 1 ! Y2 $end
$upscope $end
$upscope $end
$enddefinitions $end
$comment Show the parameter values. $end
$dumpall
$end
#0
$dumpvars
0+
0*
0)
0(
0'
0&
0%
1$
0#
0"
0!
$end
#10
1#
0$
1%
#20
0#
1"
0%
1&
#30
1#
0&
1'
#40
0#
0"
1!
0'
1(
#50
1#
0(
1)
#60
0#
1"
0)
1*
#70
1#
0*
1+
