Decoder/decoder.v
module decoder_3to8 (
    input a,
    input b,
    input c,
    output reg Y0,
    output reg Y1,
    output reg Y2,
    output reg Y3,
    output reg Y4,
    output reg Y5,
    output reg Y6,
    output reg Y7
);

always @(*) begin
    case ({a,b,c})
        3'b000: begin
            Y0 = 1;
            Y1 = 0;
            Y2 = 0;
            Y3 = 0;
            Y4 = 0;
            Y5 = 0;
            Y6 = 0;
            Y7 = 0;
        end
        3'b001: begin
            Y0 = 0;
            Y1 = 1;
            Y2 = 0;
            Y3 = 0;
            Y4 = 0;
            Y5 = 0;
            Y6 = 0;
            Y7 = 0;
        end
        3'b010: begin
            Y0 = 0;
            Y1 = 0;
            Y2 = 1;
            Y3 = 0;
            Y4 = 0;
            Y5 = 0;
            Y6 = 0;
            Y7 = 0;
        end
        3'b011: begin
            Y0 = 0;
            Y1 = 0;
            Y2 = 0;
            Y3 = 1;
            Y4 = 0;
            Y5 = 0;
            Y6 = 0;
            Y7 = 0;
        end
        3'b100: begin
            Y0 = 0;
            Y1 = 0;
            Y2 = 0;
            Y3 = 0;
            Y4 = 1;
            Y5 = 0;
            Y6 = 0;
            Y7 = 0;
        end
        3'b101: begin
            Y0 = 0;
            Y1 = 0;
            Y2 = 0;
            Y3 = 0;
            Y4 = 0;
            Y5 = 1;
            Y6 = 0;
            Y7 = 0;
        end
        3'b110: begin
            Y0 = 0;
            Y1 = 0;
            Y2 = 0;
            Y3 = 0;
            Y4 = 0;
            Y5 = 0;
            Y6 = 1;
            Y7 = 0;
        end
        3'b111: begin
            Y0 = 0;
            Y1 = 0;
            Y2 = 0;
            Y3 = 0;
            Y4 = 0;
            Y5 = 0;
            Y6 = 0;
            Y7 = 1;
        end
    endcase
end
endmodule

Decoder/decoder_tb.v
module decoder_3to8_tb;
reg a;
reg b;
reg c;
wire Y0;
wire Y1;
wire Y2;
wire Y3;
wire Y4;
wire Y5;
wire Y6;
wire Y7;

decoder_3to8 uut (
    .a(a),
    .b(b),
    .c(c),
    .Y0(Y0),
    .Y1(Y1),
    .Y2(Y2),
    .Y3(Y3),
    .Y4(Y4),
    .Y5(Y5),
    .Y6(Y6),
    .Y7(Y7)
);

initial begin
    $dumpfile("decoder_3to8_tb.vcd");
    $dumpvars(0, decoder_3to8_tb);
    $monitor("a=%b, b=%b, c=%b | Y0=%b, Y1=%b, Y2=%b, Y3=%b, Y4=%b, Y5=%b, Y6=%b, Y7=%b", a, b, c, Y0, Y1, Y2, Y3, Y4, Y5, Y6, Y7);
    a = 0; b = 0; c = 0; #10;
    a = 0; b = 0; c = 1; #10;
    a = 0; b = 1; c = 0; #10;
    a = 0; b = 1; c = 1; #10;
    a = 1; b = 0; c = 0; #10;
    a = 1; b = 0; c = 1; #10;
    a = 1; b = 1; c = 0; #10;
    a = 1; b = 1; c = 1; #10;
end
endmodule

Decoder/decoder_3to8_tb.vcd
$date
	Mon Jun 22 19:34:00 2026
$end
$version
	Icarus Verilog
$end
$timescale
	1s
$end
$scope module decoder_3to8_tb $end
$var wire 1 ! Y7 $end
$var wire 1 " Y6 $end
$var wire 1 # Y5 $end
$var wire 1 $ Y4 $end
$var wire 1 % Y3 $end
$var wire 1 & Y2 $end
$var wire 1 ' Y1 $end
$var wire 1 ( Y0 $end
$var reg 1 ) a $end
$var reg 1 * b $end
$var reg 1 + c $end
$scope module uut $end
$var wire 1 ) a $end
$var wire 1 * b $end
$var wire 1 + c $end
$var reg 1 ( Y0 $end
$var reg 1 ' Y1 $end
$var reg 1 & Y2 $end
$var reg 1 % Y3 $end
$var reg 1 $ Y4 $end
$var reg 1 # Y5 $end
$var reg 1 " Y6 $end
$var reg 1 ! Y7 $end
$upscope $end
$upscope $end
$enddefinitions $end
$comment Show the parameter values. $end
$dumpall
$end
#0
$dumpvars
0+
0*
0)
1(
0'
0&
0%
0$
0#
0"
0!
$end
#10
1'
0(
1+
#20
1&
0'
0+
1*
#30
1%
0&
1+
#40
1$
0%
0+
0*
1)
#50
1#
0$
1+
#60
1"
0#
0+
1*
#70
1!
0"
1+
